splitvid/__init__.py
splitvid-0.1.1.dist-info/COPYING
splitvid-0.1.1.dist-info/WHEEL
splitvid-0.1.1.dist-info/METADATA
splitvid-0.1.1.dist-info/RECORD
